mygnuhealth/__init__.py
mygnuhealth/about.py
mygnuhealth/bluetooth_settings.py
mygnuhealth/book_of_life.py
mygnuhealth/contributors.txt
mygnuhealth/core.py
mygnuhealth/date_picker.py
mygnuhealth/fedlogin.py
mygnuhealth/lang.py
mygnuhealth/main.py
mygnuhealth/myghconf.py
mygnuhealth/network_settings.py
mygnuhealth/page_of_life.py
mygnuhealth/profile_settings.py
mygnuhealth/tracker_bio_cardio.py
mygnuhealth/tracker_bio_glucose.py
mygnuhealth/tracker_bio_osat.py
mygnuhealth/tracker_bio_weight.py
mygnuhealth/tracker_lifestyle_nutrition.py
mygnuhealth/tracker_lifestyle_pactivity.py
mygnuhealth/tracker_lifestyle_sleep.py
mygnuhealth/tracker_lifestyle_social.py
mygnuhealth/tracker_psycho_mood.py
mygnuhealth/user_account.py
mygnuhealth/data/variants.db
mygnuhealth/data/locale/mygnuhealth.pot
mygnuhealth/data/locale/de/LC_MESSAGES/mygnuhealth.mo
mygnuhealth/data/locale/de/LC_MESSAGES/mygnuhealth.po
mygnuhealth/data/locale/en/LC_MESSAGES/mygnuhealth.mo
mygnuhealth/data/locale/en/LC_MESSAGES/mygnuhealth.po
mygnuhealth/data/locale/es/LC_MESSAGES/mygnuhealth.mo
mygnuhealth/data/locale/es/LC_MESSAGES/mygnuhealth.po
mygnuhealth/data/locale/fr/LC_MESSAGES/mygnuhealth.mo
mygnuhealth/data/locale/fr/LC_MESSAGES/mygnuhealth.po
mygnuhealth/data/locale/zh_CN/LC_MESSAGES/mygnuhealth.mo
mygnuhealth/data/locale/zh_CN/LC_MESSAGES/mygnuhealth.po
mygnuhealth/images/InfiniTime.png
mygnuhealth/images/activity-square-icon.png
mygnuhealth/images/background_color_soft.png
mygnuhealth/images/bio-button.png
mygnuhealth/images/bluetooth_settings-icon.png
mygnuhealth/images/book_of_life-button.png
mygnuhealth/images/book_of_life-icon.png
mygnuhealth/images/btdevice.png
mygnuhealth/images/calories-icon.png
mygnuhealth/images/cardio-icon.png
mygnuhealth/images/documents-icon.png
mygnuhealth/images/done-button.png
mygnuhealth/images/emergency-icon.png
mygnuhealth/images/energy0.png
mygnuhealth/images/energy1.png
mygnuhealth/images/energy2.png
mygnuhealth/images/energy3.png
mygnuhealth-2.2.1.dist-info/LICENSE
mygnuhealth-2.2.1.dist-info/METADATA
mygnuhealth-2.2.1.dist-info/WHEEL
mygnuhealth-2.2.1.dist-info/entry_points.txt
mygnuhealth-2.2.1.dist-info/top_level.txt
mygnuhealth-2.2.1.dist-info/RECORD
