Metadata-Version: 2.1
Name: mygnuhealth
Version: 2.2.1
Summary: The GNU Health Personal Health Record
Author-email: Luis Falcon <falcon@gnuhealth.org>
License: GPL v3+
Project-URL: Homepage, https://www.gnuhealth.org
Project-URL: Documentation, https://www.gnuhealth.org/docs/mygnuhealth/
Project-URL: Repository, https://hg.savannah.gnu.org/hgweb/health-mygnuhealth
Keywords: eHealth,PHR,mHealth,GNUHealth
Classifier: Development Status :: 5 - Production/Stable
Classifier: Environment :: X11 Applications
Classifier: Intended Audience :: Developers
Classifier: Intended Audience :: End Users/Desktop
Classifier: Intended Audience :: Healthcare Industry
Classifier: Intended Audience :: Science/Research
Classifier: License :: OSI Approved :: GNU General Public License (GPL)
Classifier: Operating System :: POSIX
Classifier: Programming Language :: Python :: 3
Classifier: Topic :: Scientific/Engineering :: Bio-Informatics
Classifier: Topic :: Scientific/Engineering :: Medical Science Apps.
Classifier: Natural Language :: English
Requires-Python: >=3.9
License-File: LICENSE
Requires-Dist: kivy
Requires-Dist: python-dateutil
Requires-Dist: pygal
Requires-Dist: requests
Requires-Dist: tinydb
Requires-Dist: bcrypt
Requires-Dist: cairosvg
Requires-Dist: tinycss
Requires-Dist: cssselect
Requires-Dist: bleak
